py_admetric/__init__.py
py_admetric/py_admetric.py
py_admetric/utils.py
py_admetric-0.0.1.dist-info/LICENSE
py_admetric-0.0.1.dist-info/METADATA
py_admetric-0.0.1.dist-info/WHEEL
py_admetric-0.0.1.dist-info/top_level.txt
py_admetric-0.0.1.dist-info/RECORD
