Metadata-Version: 2.1
Name: py-admetric
Version: 0.0.1
Summary: Provide calculation methods often used in digital advertising industry
Home-page: https://github.com/otomikesuy/py-admetric
Author: otomikesuy
License: UNKNOWN
Platform: UNKNOWN
Classifier: Development Status :: 2 - Pre-Alpha
Classifier: License :: OSI Approved :: MIT License
Classifier: Programming Language :: Python :: 3.9
Requires-Python: >=3.9.5
License-File: LICENSE
